get_latest_version/__init__.py
get_latest_version/__version__.py
get_latest_version/dockerhub.py
get_latest_version/functions.py
get_latest_version/github.py
get_latest_version/py.typed
get_latest_version/pypi.py
get_latest_version-1.0.3.dist-info/licenses/LICENSE
get_latest_version-1.0.3.dist-info/METADATA
get_latest_version-1.0.3.dist-info/WHEEL
get_latest_version-1.0.3.dist-info/top_level.txt
get_latest_version-1.0.3.dist-info/RECORD
