Metadata-Version: 2.4
Name: get_latest_version
Version: 1.0.3
Summary: Python module to get the latest version for various package types.
Author-email: Joe Pitt <joe.pitt@joepitt.co.uk>
License-Expression: GPL-3.0-only
Project-URL: Source, https://github.com/joepitt91/latest_version
Classifier: Development Status :: 4 - Beta
Classifier: Intended Audience :: Developers
Classifier: Natural Language :: English
Classifier: Operating System :: OS Independent
Classifier: Programming Language :: Python :: 3 :: Only
Classifier: Topic :: Software Development
Classifier: Topic :: Software Development :: Build Tools
Classifier: Topic :: Software Development :: Version Control
Classifier: Typing :: Typed
Requires-Python: ~=3.8
License-File: LICENSE
Requires-Dist: semver~=3.0.4
Requires-Dist: requests~=2.32.3
Dynamic: license-file
